odoo/addons/stock_release_channel_warehouse_calendar/README.rst
odoo/addons/stock_release_channel_warehouse_calendar/__init__.py
odoo/addons/stock_release_channel_warehouse_calendar/__manifest__.py
odoo/addons/stock_release_channel_warehouse_calendar/i18n/it.po
odoo/addons/stock_release_channel_warehouse_calendar/i18n/stock_release_channel_warehouse_calendar.pot
odoo/addons/stock_release_channel_warehouse_calendar/models/__init__.py
odoo/addons/stock_release_channel_warehouse_calendar/models/stock_release_channel.py
odoo/addons/stock_release_channel_warehouse_calendar/readme/CONTRIBUTORS.md
odoo/addons/stock_release_channel_warehouse_calendar/readme/DESCRIPTION.md
odoo/addons/stock_release_channel_warehouse_calendar/static/description/icon.png
odoo/addons/stock_release_channel_warehouse_calendar/static/description/index.html
odoo/addons/stock_release_channel_warehouse_calendar/tests/__init__.py
odoo/addons/stock_release_channel_warehouse_calendar/tests/test_channel_delivery_date.py
odoo_addon_stock_release_channel_warehouse_calendar-18.0.1.0.0.2.dist-info/METADATA
odoo_addon_stock_release_channel_warehouse_calendar-18.0.1.0.0.2.dist-info/WHEEL
odoo_addon_stock_release_channel_warehouse_calendar-18.0.1.0.0.2.dist-info/top_level.txt
odoo_addon_stock_release_channel_warehouse_calendar-18.0.1.0.0.2.dist-info/RECORD
